<?xml version="1.0" encoding="gbk" ?>
<package>
   <RS485 name="RS485A" desc="RS485´®ÐÐ×ÜÏß">
    <PortName>/dev/ttyS0</PortName>
    <BaudRate>9600</BaudRate>
    <DataBits>8</DataBits>
    <StopBits>1</StopBits>
    <Parity>0</Parity>
    <TotalTimeOut>1000</TotalTimeOut>
    <IntervalTimeOut>200</IntervalTimeOut>
    <InBufferSize>1024</InBufferSize>
    <OutBufferSize>1024</OutBufferSize>
  </RS485>
<MonitorUnit name="MU1" interval="7000" protocolname="MMXN" port="RS485A" manufacturer="neri" cycleid="" mac="9" ytime="1">
     <MeasurePoint  deviceid="GC0007" IEDName="NEPRI_CMD" id="MMXN7" checktime="">
  		  <param name="SmpTm" />
     	  <param name="Amp" />
     </MeasurePoint>
</MonitorUnit>
</package>
